hjflow/__init__.py
hjflow/args.py
hjflow/conf.py
hjflow/flow.py
hjflow-0.0.1.dist-info/LICENSE
hjflow-0.0.1.dist-info/METADATA
hjflow-0.0.1.dist-info/WHEEL
hjflow-0.0.1.dist-info/top_level.txt
hjflow-0.0.1.dist-info/RECORD
