Metadata-Version: 2.1
Name: hjflow
Version: 0.0.1
Summary: Library for defining program flow in HJSON
Author: Ville Ahlgren
License-File: LICENSE
Requires-Dist: hjson
